verilog/systolic_array_4x4/fsm_pe.v
module fsm_pe (RD, FDi, clk, rst, GD, FDo, result, result_ld);
	parameter DATA_WIDTH=16,
			reset=0,
			calc_0=1,
			calc_1=2,
			ld_result=3,
			drain_0=4,
			drain_1=5;
	
	input [(2*DATA_WIDTH)-1:0] RD;
	input [DATA_WIDTH-1:0] FDi;
	input clk, rst, result_ld;
	
	output reg [DATA_WIDTH-1:0] FDo;
	output reg [(2*DATA_WIDTH)-1:0] GD;
	output reg [(2*DATA_WIDTH)-1:0] result;
	
	wire [(2*DATA_WIDTH)-1:0] multi;
	
	reg[2:0]  p_state, n_state;	
	
	
	always @ (p_state,result_ld)
	
    		begin
            
     		   case (p_state)
        
			reset: // state 0
			begin
				result <= 0;
				FDo <= 0;
				GD <= 0;
				
				// next state
				n_state=calc_0;
			end
			
			calc_0: // state 1
			begin
				result <= result + multi;
				FDo <= FDi;
				GD <= RD;
				
				// next state
				if (result_ld)
					n_state=ld_result;
				else
					n_state=calc_1;			
			end
	
			calc_1: // state 2
			begin
				result <= result + multi;
				FDo <= FDi;
				GD <= RD;
				
				// next state
				if (result_ld)
					n_state=ld_result;
				else
					n_state=calc_0;			
			end
	
			ld_result: // state 3
			begin
				GD <= result;
				
				// next state
				n_state=drain_0;
			end
			
			drain_0: // state 4
			begin
				GD <= RD;
				
				// next state
				n_state=drain_1;
			end
			
			drain_1: // state 5
			begin
				GD <= RD;
				
				// next state
				n_state=drain_0;
			end

			default: n_state= reset;

		   endcase
		
	end // end of always
	
	// MAC operation
		assign multi = RD*FDi;
		
	
  	always @ (posedge clk)
  	
    		begin // always    
       			if (rst)
        			   p_state=reset; 
			else
     				   p_state=n_state;
   		 end // always
endmodule

verilog/systolic_array_4x4/systolic_array_4x4.v
`timescale 1ns/1ns
module systolic_array_4x4(
		      FDi0, FDi4, FDi8, FDi12,
		      RD0, RD1, RD2, RD3,
		      clk, rst, result_ld,
		      FDo0, FDo4, FDo8, FDo12,
		      sa_GD0, sa_GD1, sa_GD2, sa_GD3);
	parameter DATA_WIDTH=16;
	
	input [DATA_WIDTH-1:0] FDi0, FDi4, FDi8, FDi12;
	input [(2*DATA_WIDTH)-1:0] RD0, RD1, RD2, RD3;
	input clk, rst, result_ld;
	
	output [(2*DATA_WIDTH)-1:0] sa_GD0, sa_GD1, sa_GD2, sa_GD3;
	output [DATA_WIDTH-1:0] FDo0, FDo4, FDo8, FDo12;
	
	
	wire [(2*DATA_WIDTH)-1:0] result[0:15];
	
		
	wire [(2*DATA_WIDTH)-1:0] GD[0:15];
	wire [DATA_WIDTH-1:0] FDo[0:15];
	

	//from north and west
	fsm_pe P0 (RD0, FDi0, clk, rst, GD[0], FDo0, result[0], result_ld);
	//from north
	fsm_pe P1 (RD1, FDo0, clk, rst, GD[1], FDo[1], result[1], result_ld);
	fsm_pe P2 (RD2, FDo[1], clk, rst, GD[2], FDo[2], result[2], result_ld);
	fsm_pe P3 (RD3, FDo[2], clk, rst, GD[3], FDo[3], result[3], result_ld);
	
	//from west
	fsm_pe P4 (GD[0], FDi4, clk, rst, GD[4], FDo4, result[4], result_ld);
	fsm_pe P8 (GD[4], FDi8, clk, rst, GD[8], FDo8, result[8], result_ld);
	fsm_pe P12 (GD[8], FDi12, clk, rst, sa_GD0, FDo12, result[12], result_ld);
	
	//no direct inputs
	//second row
	fsm_pe P5 (GD[1], FDo4, clk, rst, GD[5], FDo[5], result[5], result_ld);
	fsm_pe P6 (GD[2], FDo[5], clk, rst, GD[6], FDo[6], result[6], result_ld);
	fsm_pe P7 (GD[3], FDo[6], clk, rst, GD[7], FDo[7], result[7], result_ld);
	//third row
	fsm_pe P9 (GD[5], FDo8, clk, rst, GD[9], FDo[9], result[9], result_ld);
	fsm_pe P10 (GD[6], FDo[9], clk, rst, GD[10], FDo[10], result[10], result_ld);
	fsm_pe P11 (GD[7], FDo[10], clk, rst, GD[11], FDo[11], result[11], result_ld);
	//fourth row
	fsm_pe P13 (GD[9], FDo12, clk, rst, sa_GD1, FDo[13], result[13], result_ld);
	fsm_pe P14 (GD[10], FDo[13], clk, rst, sa_GD2, FDo[14], result[14], result_ld);
	fsm_pe P15 (GD[11], FDo[14], clk, rst, sa_GD3, FDo[15], result[15], result_ld);
	
		      
endmodule

verilog/systolic_array_4x4/tb_systolic_array_4x4.v
`timescale 1ns/1ns

module tb_systolic_array_4x4;

parameter DATA_WIDTH=16,
		period=10,
		start_ld=15,
		sys_rst=15,
		num_of_clk=30;

	
	
	reg [DATA_WIDTH-1:0] tb_FDi0, tb_FDi4, tb_FDi8, tb_FDi12;
	reg [(2*DATA_WIDTH)-1:0] tb_RD0, tb_RD1, tb_RD2, tb_RD3;
	
	wire [DATA_WIDTH-1:0] tb_FDo0, tb_FDo4, tb_FDo8, tb_FDo12;
	wire [(2*DATA_WIDTH)-1:0] tb_GD0, tb_GD1, tb_GD2, tb_GD3;
	
	reg tb_clk, tb_rst, tb_result_ld;
	
	integer inFromFile_A, inFromFile_B, A_file, B_file;
	
	systolic_array_4x4 sa_4x4_inst(
		.clk(tb_clk),
		.rst(tb_rst),
		.result_ld(tb_result_ld),
		.RD0(tb_RD0),
		.RD1(tb_RD1),
		.RD2(tb_RD2),
		.RD3(tb_RD3),
		.FDi0(tb_FDi0),
		.FDi4(tb_FDi4),
		.FDi8(tb_FDi8),
		.FDi12(tb_FDi12),
		.FDo0(tb_FDo0),
		.FDo4(tb_FDo4),
		.FDo8(tb_FDo8),
		.FDo12(tb_FDo12),
		.sa_GD0(tb_GD0),
		.sa_GD1(tb_GD1),
		.sa_GD2(tb_GD2),
		.sa_GD3(tb_GD3)
	);
	
// Reading B File
initial begin
	
#start_ld;
              
  	B_file=$fopen("B_TB.txt","r");
      
		while (! $feof(B_file)) 
			begin         
				inFromFile_B= $fscanf(B_file,"%d %d %d %d\n", tb_RD0, tb_RD1, tb_RD2, tb_RD3);
				#(2*period);                         
			end
                  
	$fclose(B_file);
      
end // End of Reading B

// Reading A File
initial begin
	
#start_ld;

	A_file=$fopen("A_TB.txt","r");
      
	while (! $feof(A_file)) 
		begin         
			inFromFile_A=$fscanf(A_file,"%d %d %d %d\n",tb_FDi0, tb_FDi4, tb_FDi8, tb_FDi12);
			#(2*period);
		end
                  
	$fclose(A_file);
      
end // End of input file

initial begin // rst 
	tb_rst <= 1;
	tb_clk <= 0;
	#(sys_rst);
	tb_rst <= 0;

end

initial begin // clock
	
	repeat(num_of_clk)
		#period tb_clk <= ~tb_clk;
end

initial begin // result_ld

	tb_result_ld=0;
	#(223);
	tb_result_ld=1;
	#(2*period);
	tb_result_ld=0;

end
	
initial begin
	$dumpfile("VCD_FILE.vcd");
	$dumpvars;
end
			      
endmodule

verilog/systolic_array_4x4/vcd/VCD_FILE.vcd
$date
	Mon Dec 18 17:11:10 2023
$end
$version
	Icarus Verilog
$end
$timescale
	1ns
$end
$scope module tb_systolic_array_4x4 $end
$var wire 32 ! tb_GD3 [31:0] $end
$var wire 32 " tb_GD2 [31:0] $end
$var wire 32 # tb_GD1 [31:0] $end
$var wire 32 $ tb_GD0 [31:0] $end
$var wire 16 % tb_FDo8 [15:0] $end
$var wire 16 & tb_FDo4 [15:0] $end
$var wire 16 ' tb_FDo12 [15:0] $end
$var wire 16 ( tb_FDo0 [15:0] $end
$var reg 16 ) tb_FDi0 [15:0] $end
$var reg 16 * tb_FDi12 [15:0] $end
$var reg 16 + tb_FDi4 [15:0] $end
$var reg 16 , tb_FDi8 [15:0] $end
$var reg 32 - tb_RD0 [31:0] $end
$var reg 32 . tb_RD1 [31:0] $end
$var reg 32 / tb_RD2 [31:0] $end
$var reg 32 0 tb_RD3 [31:0] $end
$var reg 1 1 tb_clk $end
$var reg 1 2 tb_result_ld $end
$var reg 1 3 tb_rst $end
$var integer 32 4 A_file [31:0] $end
$var integer 32 5 B_file [31:0] $end
$var integer 32 6 inFromFile_A [31:0] $end
$var integer 32 7 inFromFile_B [31:0] $end
$scope module sa_4x4_inst $end
$var wire 16 8 FDi0 [15:0] $end
$var wire 16 9 FDi12 [15:0] $end
$var wire 16 : FDi4 [15:0] $end
$var wire 16 ; FDi8 [15:0] $end
$var wire 32 < RD0 [31:0] $end
$var wire 32 = RD1 [31:0] $end
$var wire 32 > RD2 [31:0] $end
$var wire 32 ? RD3 [31:0] $end
$var wire 1 1 clk $end
$var wire 1 2 result_ld $end
$var wire 1 3 rst $end
$var wire 32 @ sa_GD3 [31:0] $end
$var wire 32 A sa_GD2 [31:0] $end
$var wire 32 B sa_GD1 [31:0] $end
$var wire 32 C sa_GD0 [31:0] $end
$var wire 16 D FDo8 [15:0] $end
$var wire 16 E FDo4 [15:0] $end
$var wire 16 F FDo12 [15:0] $end
$var wire 16 G FDo0 [15:0] $end
$scope module P0 $end
$var wire 16 H FDi [15:0] $end
$var wire 32 I RD [31:0] $end
$var wire 1 1 clk $end
$var wire 1 2 result_ld $end
$var wire 1 3 rst $end
$var wire 32 J multi [31:0] $end
$var reg 16 K FDo [15:0] $end
$var reg 32 L GD [31:0] $end
$var reg 3 M n_state [2:0] $end
$var reg 3 N p_state [2:0] $end
$var reg 32 O result [31:0] $end
$upscope $end
$scope module P1 $end
$var wire 16 P FDi [15:0] $end
$var wire 32 Q RD [31:0] $end
$var wire 1 1 clk $end
$var wire 1 2 result_ld $end
$var wire 1 3 rst $end
$var wire 32 R multi [31:0] $end
$var reg 16 S FDo [15:0] $end
$var reg 32 T GD [31:0] $end
$var reg 3 U n_state [2:0] $end
$var reg 3 V p_state [2:0] $end
$var reg 32 W result [31:0] $end
$upscope $end
$scope module P10 $end
$var wire 1 1 clk $end
$var wire 1 2 result_ld $end
$var wire 1 3 rst $end
$var wire 32 X multi [31:0] $end
$var wire 32 Y RD [31:0] $end
$var wire 16 Z FDi [15:0] $end
$var reg 16 [ FDo [15:0] $end
$var reg 32 \ GD [31:0] $end
$var reg 3 ] n_state [2:0] $end
$var reg 3 ^ p_state [2:0] $end
$var reg 32 _ result [31:0] $end
$upscope $end
$scope module P11 $end
$var wire 16 ` FDi [15:0] $end
$var wire 1 1 clk $end
$var wire 1 2 result_ld $end
$var wire 1 3 rst $end
$var wire 32 a multi [31:0] $end
$var wire 32 b RD [31:0] $end
$var reg 16 c FDo [15:0] $end
$var reg 32 d GD [31:0] $end
$var reg 3 e n_state [2:0] $end
$var reg 3 f p_state [2:0] $end
$var reg 32 g result [31:0] $end
$upscope $end
$scope module P12 $end
$var wire 16 h FDi [15:0] $end
$var wire 1 1 clk $end
$var wire 1 2 result_ld $end
$var wire 1 3 rst $end
$var wire 32 i multi [31:0] $end
$var wire 32 j RD [31:0] $end
$var reg 16 k FDo [15:0] $end
$var reg 32 l GD [31:0] $end
$var reg 3 m n_state [2:0] $end
$var reg 3 n p_state [2:0] $end
$var reg 32 o result [31:0] $end
$upscope $end
$scope module P13 $end
$var wire 16 p FDi [15:0] $end
$var wire 1 1 clk $end
$var wire 1 2 result_ld $end
$var wire 1 3 rst $end
$var wire 32 q multi [31:0] $end
$var wire 32 r RD [31:0] $end
$var reg 16 s FDo [15:0] $end
$var reg 32 t GD [31:0] $end
$var reg 3 u n_state [2:0] $end
$var reg 3 v p_state [2:0] $end
$var reg 32 w result [31:0] $end
$upscope $end
$scope module P14 $end
$var wire 16 x FDi [15:0] $end
$var wire 32 y RD [31:0] $end
$var wire 1 1 clk $end
$var wire 1 2 result_ld $end
$var wire 1 3 rst $end
$var wire 32 z multi [31:0] $end
$var reg 16 { FDo [15:0] $end
$var reg 32 | GD [31:0] $end
$var reg 3 } n_state [2:0] $end
$var reg 3 ~ p_state [2:0] $end
$var reg 32 !" result [31:0] $end
$upscope $end
$scope module P15 $end
$var wire 16 "" FDi [15:0] $end
$var wire 32 #" RD [31:0] $end
$var wire 1 1 clk $end
$var wire 1 2 result_ld $end
$var wire 1 3 rst $end
$var wire 32 $" multi [31:0] $end
$var reg 16 %" FDo [15:0] $end
$var reg 32 &" GD [31:0] $end
$var reg 3 '" n_state [2:0] $end
$var reg 3 (" p_state [2:0] $end
$var reg 32 )" result [31:0] $end
$upscope $end
$scope module P2 $end
$var wire 16 *" FDi [15:0] $end
$var wire 32 +" RD [31:0] $end
$var wire 1 1 clk $end
$var wire 1 2 result_ld $end
$var wire 1 3 rst $end
$var wire 32 ," multi [31:0] $end
$var reg 16 -" FDo [15:0] $end
$var reg 32 ." GD [31:0] $end
$var reg 3 /" n_state [2:0] $end
$var reg 3 0" p_state [2:0] $end
$var reg 32 1" result [31:0] $end
$upscope $end
$scope module P3 $end
$var wire 16 2" FDi [15:0] $end
$var wire 32 3" RD [31:0] $end
$var wire 1 1 clk $end
$var wire 1 2 result_ld $end
$var wire 1 3 rst $end
$var wire 32 4" multi [31:0] $end
$var reg 16 5" FDo [15:0] $end
$var reg 32 6" GD [31:0] $end
$var reg 3 7" n_state [2:0] $end
$var reg 3 8" p_state [2:0] $end
$var reg 32 9" result [31:0] $end
$upscope $end
$scope module P4 $end
$var wire 16 :" FDi [15:0] $end
$var wire 32 ;" RD [31:0] $end
$var wire 1 1 clk $end
$var wire 1 2 result_ld $end
$var wire 1 3 rst $end
$var wire 32 <" multi [31:0] $end
$var reg 16 =" FDo [15:0] $end
$var reg 32 >" GD [31:0] $end
$var reg 3 ?" n_state [2:0] $end
$var reg 3 @" p_state [2:0] $end
$var reg 32 A" result [31:0] $end
$upscope $end
$scope module P5 $end
$var wire 16 B" FDi [15:0] $end
$var wire 32 C" RD [31:0] $end
$var wire 1 1 clk $end
$var wire 1 2 result_ld $end
$var wire 1 3 rst $end
$var wire 32 D" multi [31:0] $end
$var reg 16 E" FDo [15:0] $end
$var reg 32 F" GD [31:0] $end
$var reg 3 G" n_state [2:0] $end
$var reg 3 H" p_state [2:0] $end
$var reg 32 I" result [31:0] $end
$upscope $end
$scope module P6 $end
$var wire 16 J" FDi [15:0] $end
$var wire 32 K" RD [31:0] $end
$var wire 1 1 clk $end
$var wire 1 2 result_ld $end
$var wire 1 3 rst $end
$var wire 32 L" multi [31:0] $end
$var reg 16 M" FDo [15:0] $end
$var reg 32 N" GD [31:0] $end
$var reg 3 O" n_state [2:0] $end
$var reg 3 P" p_state [2:0] $end
$var reg 32 Q" result [31:0] $end
$upscope $end
$scope module P7 $end
$var wire 16 R" FDi [15:0] $end
$var wire 32 S" RD [31:0] $end
$var wire 1 1 clk $end
$var wire 1 2 result_ld $end
$var wire 1 3 rst $end
$var wire 32 T" multi [31:0] $end
$var reg 16 U" FDo [15:0] $end
$var reg 32 V" GD [31:0] $end
$var reg 3 W" n_state [2:0] $end
$var reg 3 X" p_state [2:0] $end
$var reg 32 Y" result [31:0] $end
$upscope $end
$scope module P8 $end
$var wire 16 Z" FDi [15:0] $end
$var wire 32 [" RD [31:0] $end
$var wire 1 1 clk $end
$var wire 1 2 result_ld $end
$var wire 1 3 rst $end
$var wire 32 \" multi [31:0] $end
$var reg 16 ]" FDo [15:0] $end
$var reg 32 ^" GD [31:0] $end
$var reg 3 _" n_state [2:0] $end
$var reg 3 `" p_state [2:0] $end
$var reg 32 a" result [31:0] $end
$upscope $end
$scope module P9 $end
$var wire 16 b" FDi [15:0] $end
$var wire 32 c" RD [31:0] $end
$var wire 1 1 clk $end
$var wire 1 2 result_ld $end
$var wire 1 3 rst $end
$var wire 32 d" multi [31:0] $end
$var reg 16 e" FDo [15:0] $end
$var reg 32 f" GD [31:0] $end
$var reg 3 g" n_state [2:0] $end
$var reg 3 h" p_state [2:0] $end
$var reg 32 i" result [31:0] $end
$upscope $end
$upscope $end
$upscope $end
$enddefinitions $end
#0
$dumpvars
bx i"
bx h"
b0 g"
bx f"
bx e"
bx d"
bx c"
bx b"
bx a"
bx `"
b0 _"
bx ^"
bx ]"
bx \"
bx ["
bx Z"
bx Y"
bx X"
b0 W"
bx V"
bx U"
bx T"
bx S"
bx R"
bx Q"
bx P"
b0 O"
bx N"
bx M"
bx L"
bx K"
bx J"
bx I"
bx H"
b0 G"
bx F"
bx E"
bx D"
bx C"
bx B"
bx A"
bx @"
b0 ?"
bx >"
bx ="
bx <"
bx ;"
bx :"
bx 9"
bx 8"
b0 7"
bx 6"
bx 5"
bx 4"
bx 3"
bx 2"
bx 1"
bx 0"
b0 /"
bx ."
bx -"
bx ,"
bx +"
bx *"
bx )"
bx ("
b0 '"
bx &"
bx %"
bx $"
bx #"
bx ""
bx !"
bx ~
b0 }
bx |
bx {
bx z
bx y
bx x
bx w
bx v
b0 u
bx t
bx s
bx r
bx q
bx p
bx o
bx n
b0 m
bx l
bx k
bx j
bx i
bx h
bx g
bx f
b0 e
bx d
bx c
bx b
bx a
bx `
bx _
bx ^
b0 ]
bx \
bx [
bx Z
bx Y
bx X
bx W
bx V
b0 U
bx T
bx S
bx R
bx Q
bx P
bx O
bx N
b0 M
bx L
bx K
bx J
bx I
bx H
bx G
bx F
bx E
bx D
bx C
bx B
bx A
bx @
bx ?
bx >
bx =
bx <
bx ;
bx :
bx 9
bx 8
bx 7
bx 6
bx 5
bx 4
13
02
01
bx 0
bx /
bx .
bx -
bx ,
bx +
bx *
bx )
bx (
bx '
bx &
bx %
bx $
bx #
bx "
bx !
$end
#10
b0 L
b0 ;"
b0 (
b0 G
b0 K
b0 P
b0 O
b0 D"
b0 T
b0 C"
b0 S
b0 *"
b0 W
b0 L"
b0 ."
b0 K"
b0 -"
b0 2"
b0 1"
b0 T"
b0 6"
b0 S"
b0 5"
b0 9"
b0 >"
b0 ["
b0 &
b0 E
b0 ="
b0 B"
b0 A"
b0 j
b0 ^"
b0 d"
b0 %
b0 D
b0 ]"
b0 b"
b0 a"
b0 $
b0 C
b0 l
b0 q
b0 '
b0 F
b0 k
b0 p
b0 o
b0 F"
b0 c"
b0 E"
b0 J"
b0 I"
b0 X
b0 Y
b0 N"
b0 M"
b0 R"
b0 Q"
b0 a
b0 b
b0 V"
b0 U"
b0 Y"
b0 r
b0 f"
b0 Z
b0 e"
b0 i"
b0 z
b0 \
b0 y
b0 [
b0 `
b0 _
b0 $"
b0 d
b0 #"
b0 c
b0 g
b0 #
b0 B
b0 t
b0 s
b0 x
b0 w
b0 "
b0 A
b0 |
b0 {
b0 ""
b0 !"
b0 !
b0 @
b0 &"
b0 %"
b0 )"
b1 M
b1 U
b1 /"
b1 7"
b1 ?"
b1 _"
b1 m
b1 G"
b1 O"
b1 W"
b1 g"
b1 ]
b1 e
b1 u
b1 }
b1 '"
b0 N
b0 V
b0 0"
b0 8"
b0 @"
b0 `"
b0 n
b0 H"
b0 P"
b0 X"
b0 h"
b0 ^
b0 f
b0 v
b0 ~
b0 ("
11
#15
03
b100 6
b0 i
b0 *
b0 9
b0 h
b0 \"
b0 ,
b0 ;
b0 Z"
b0 <"
b0 +
b0 :
b0 :"
b1110101 J
b1101 )
b1101 8
b1101 H
b10000000000000000000000000000100 4
b100 7
b0 4"
b0 0
b0 ?
b0 3"
b0 ,"
b0 /
b0 >
b0 +"
b0 R
b0 .
b0 =
b0 Q
b1001 -
b1001 <
b1001 I
b10000000000000000000000000000011 5
#20
01
#30
b1001 L
b1001 ;"
b1101 (
b1101 G
b1101 K
b1101 P
b1110101 O
b10 '"
b10 }
b10 u
b10 e
b10 ]
b10 g"
b10 W"
b10 O"
b10 G"
b10 m
b10 _"
b10 ?"
b10 7"
b10 /"
b10 U
b10 M
b1 ("
b1 ~
b1 v
b1 f
b1 ^
b1 h"
b1 X"
b1 P"
b1 H"
b1 n
b1 `"
b1 @"
b1 8"
b1 0"
b1 V
b1 N
11
#35
b1111110 <"
b1110 +
b1110 :
b1110 :"
b1100 )
b1100 8
b1100 H
b1001110 R
b110 .
b110 =
b110 Q
b110000 J
b100 -
b100 <
b100 I
#40
01
#50
b111000 <"
b100 L
b100 ;"
b1001000 R
b1100 (
b1100 G
b1100 K
b1100 P
b10100101 O
b1010100 D"
b110 T
b110 C"
b1101 S
b1101 *"
b1001110 W
b1001 >"
b1001 ["
b1110 &
b1110 E
b1110 ="
b1110 B"
b1111110 A"
b1 M
b1 U
b1 /"
b1 7"
b1 ?"
b1 _"
b1 m
b1 G"
b1 O"
b1 W"
b1 g"
b1 ]
b1 e
b1 u
b1 }
b1 '"
b10 N
b10 V
b10 0"
b10 8"
b10 @"
b10 `"
b10 n
b10 H"
b10 P"
b10 X"
b10 h"
b10 ^
b10 f
b10 v
b10 ~
b10 ("
11
#55
b1010001 \"
b1001 ,
b1001 ;
b1001 Z"
b10100 <"
b101 +
b101 :
b101 :"
b100100 J
b1001 )
b1001 8
b1001 H
b10011100 ,"
b1100 /
b1100 >
b1100 +"
b110000 R
b100 .
b100 =
b100 Q
#60
01
#70
b110110 d"
b110 F"
b110 c"
b10101000 L"
b1110 E"
b1110 J"
b1010100 I"
b1001 j
b1001 ^"
b1001 %
b1001 D
b1001 ]"
b1001 b"
b1010001 a"
b100100 \"
b100 >"
b100 ["
b101 &
b101 E
b101 ="
b101 B"
b10010010 A"
b1100 ."
b1100 K"
b1101 -"
b1101 2"
b10011100 1"
b10100 D"
b100 T
b100 C"
b10010000 ,"
b1100 S
b1100 *"
b1111110 W
b100100 R
b1001 (
b1001 G
b1001 K
b1001 P
b11001001 O
b10 '"
b10 }
b10 u
b10 e
b10 ]
b10 g"
b10 W"
b10 O"
b10 G"
b10 m
b10 _"
b10 ?"
b10 7"
b10 /"
b10 U
b10 M
b1 ("
b1 ~
b1 v
b1 f
b1 ^
b1 h"
b1 X"
b1 P"
b1 H"
b1 n
b1 `"
b1 @"
b1 8"
b1 0"
b1 V
b1 N
11
#75
b10010 i
b10 *
b10 9
b10 h
b1100 <"
b11 +
b11 :
b11 :"
b100 )
b100 8
b100 H
b1101000 4"
b1000 0
b1000 ?
b1000 3"
b100100 ,"
b11 /
b11 >
b11 +"
b1010001 R
b1001 .
b1001 =
b1001 Q
b11100 J
b111 -
b111 <
b111 I
#80
01
#90
b10101 <"
b111 L
b111 ;"
b100100 R
b100 (
b100 G
b100 K
b100 P
b11100101 O
b1001 T
b1001 C"
b11011 ,"
b1001 S
b1001 *"
b11001111 W
b11 ."
b11 K"
b1100000 4"
b1100 -"
b1100 2"
b11000000 1"
b1110000 T"
b1000 6"
b1000 S"
b1101 5"
b1101000 9"
b11011 D"
b11 &
b11 E
b11 ="
b11 B"
b10011110 A"
b1000 i
b100 j
b100 ^"
b1110101 a"
b1001 $
b1001 C
b1001 l
b1100 q
b10 '
b10 F
b10 k
b10 p
b10010 o
b100100 d"
b100 F"
b100 c"
b1111 L"
b101 E"
b101 J"
b1101000 I"
b1101100 X
b1100 Y
b1100 N"
b1110 M"
b1110 R"
b10101000 Q"
b110 r
b110 f"
b1001 Z
b1001 e"
b110110 i"
b1 M
b1 U
b1 /"
b1 7"
b1 ?"
b1 _"
b1 m
b1 G"
b1 O"
b1 W"
b1 g"
b1 ]
b1 e
b1 u
b1 }
b1 '"
b10 N
b10 V
b10 0"
b10 8"
b10 @"
b10 `"
b10 n
b10 H"
b10 P"
b10 X"
b10 h"
b10 ^
b10 f
b10 v
b10 ~
b10 ("
11
#95
b110000 i
b1100 *
b1100 9
b1100 h
b101000 \"
b1010 ,
b1010 ;
b1010 Z"
b11100 <"
b100 +
b100 :
b100 :"
b0 )
b0 8
b0 H
b1010100 4"
b111 0
b111 ?
b111 3"
b110000 R
b1100 .
b1100 =
b1100 Q
b0 J
b0 -
b0 <
b0 I
#100
01
#110
b110 #
b110 B
b110 t
b11000 z
b10 s
b10 x
b1100 w
b1100 \
b1100 y
b1001000 a
b1001 [
b1001 `
b1101100 _
b100 r
b100 f"
b1011010 i"
b1000 b
b1000 V"
b1110 U"
b1110000 Y"
b11011 X
b11 Y
b11 N"
b101 M"
b101 R"
b10110111 Q"
b1001 F"
b1001 c"
b1001 L"
b11 E"
b11 J"
b10000011 I"
b100 $
b100 C
b100 l
b110000 q
b1100 '
b1100 F
b1100 k
b1100 p
b1000010 o
b1011010 d"
b1010 %
b1010 D
b1010 ]"
b1010 b"
b10011101 a"
b1000110 \"
b111 >"
b111 ["
b100 &
b100 E
b100 ="
b100 B"
b10111010 A"
b100011 T"
b111 6"
b111 S"
b1100 5"
b10111100 9"
b111111 4"
b1001 -"
b1001 2"
b11011011 1"
b110000 D"
b1100 T
b1100 C"
b1100 ,"
b100 S
b100 *"
b11111111 W
b0 <"
b0 L
b0 ;"
b0 R
b0 (
b0 G
b0 K
b0 P
b10 '"
b10 }
b10 u
b10 e
b10 ]
b10 g"
b10 W"
b10 O"
b10 G"
b10 m
b10 _"
b10 ?"
b10 7"
b10 /"
b10 U
b10 M
b1 ("
b1 ~
b1 v
b1 f
b1 ^
b1 h"
b1 X"
b1 P"
b1 H"
b1 n
b1 `"
b1 @"
b1 8"
b1 0"
b1 V
b1 N
11
#115
b101000 i
b1010 *
b1010 9
b1010 h
b1001101 \"
b1011 ,
b1011 ;
b1011 Z"
b0 +
b0 :
b0 :"
b1001000 4"
b1000 0
b1000 ?
b1000 3"
b101000 ,"
b1010 /
b1010 >
b1010 +"
b0 .
b0 =
b0 Q
#120
01
#130
b0 T
b0 C"
b0 ,"
b0 S
b0 *"
b1010 ."
b1010 K"
b100000 4"
b100 -"
b100 2"
b100000011 1"
b1000 6"
b1000 S"
b1001 5"
b100000100 9"
b0 \"
b0 >"
b0 ["
b0 D"
b0 &
b0 E
b0 ="
b0 B"
b1000110 i
b111 j
b111 ^"
b1011 %
b1011 D
b1011 ]"
b1011 b"
b11101010 a"
b1010 '
b1010 F
b1010 k
b1010 p
b1101010 o
b10000100 d"
b1100 F"
b1100 c"
b101000 L"
b100 E"
b100 J"
b10110011 I"
b11000 T"
b11 M"
b11 R"
b11000000 Q"
b111111 a
b111 b
b111 V"
b101 U"
b10010011 Y"
b1011010 q
b1001 r
b1001 f"
b11110 X
b1010 Z
b1010 e"
b10110100 i"
b11 \
b11 y
b10000111 _
b10000 $"
b1000 d
b1000 #"
b1001 c
b1001000 g
b100 #
b100 B
b100 t
b100100 z
b1100 s
b1100 x
b111100 w
b1100 "
b1100 A
b1100 |
b10 {
b10 ""
b11000 !"
b1 M
b1 U
b1 /"
b1 7"
b1 ?"
b1 _"
b1 m
b1 G"
b1 O"
b1 W"
b1 g"
b1 ]
b1 e
b1 u
b1 }
b1 '"
b10 N
b10 V
b10 0"
b10 8"
b10 @"
b10 `"
b10 n
b10 H"
b10 P"
b10 X"
b10 h"
b10 ^
b10 f
b10 v
b10 ~
b10 ("
11
#135
b0 ,
b0 ;
b0 Z"
b1100 4"
b11 0
b11 ?
b11 3"
b0 /
b0 >
b0 +"
#140
01
#150
b1000 !
b1000 @
b1000 &"
b10 %"
b10000 )"
b11 "
b11 A
b11 |
b1100 {
b1100 ""
b111100 !"
b1001 #
b1001 B
b1001 t
b11110 z
b1010 s
b1010 x
b10010110 w
b1010100 $"
b111 d
b111 #"
b10000111 g
b1010 [
b1010 `
b10100101 _
b1111000 q
b1100 r
b1100 f"
b1011 Z
b1011 e"
b100111000 i"
b1010000 a
b1000 b
b1000 V"
b11 U"
b10101011 Y"
b1101110 X
b1010 Y
b1010 N"
b100 M"
b100 R"
b11101000 Q"
b0 F"
b0 c"
b0 E"
b0 J"
b111 $
b111 C
b111 l
b10110000 o
b0 i
b0 j
b0 ^"
b0 d"
b0 %
b0 D
b0 ]"
b0 b"
b1100 T"
b11 6"
b11 S"
b100 5"
b100010000 9"
b0 L"
b0 ."
b0 K"
b0 4"
b0 -"
b0 2"
b10 '"
b10 }
b10 u
b10 e
b10 ]
b10 g"
b10 W"
b10 O"
b10 G"
b10 m
b10 _"
b10 ?"
b10 7"
b10 /"
b10 U
b10 M
b1 ("
b1 ~
b1 v
b1 f
b1 ^
b1 h"
b1 X"
b1 P"
b1 H"
b1 n
b1 `"
b1 @"
b1 8"
b1 0"
b1 V
b1 N
11
#160
01
#170
b0 5"
b0 $
b0 C
b0 l
b0 Y
b0 N"
b0 T"
b0 M"
b0 R"
b11 b
b11 V"
b100 U"
b10110111 Y"
b0 q
b0 r
b0 f"
b0 X
b0 Z
b0 e"
b1100100 z
b1010 \
b1010 y
b100001 a
b1011 [
b1011 `
b100010011 _
b1000 d
b1000 #"
b1010 c
b11010111 g
b1100 #
b1100 B
b1100 t
b100001110 w
b1010000 $"
b1010 {
b1010 ""
b1011010 !"
b111 !
b111 @
b111 &"
b1100 %"
b1100100 )"
b1 M
b1 U
b1 /"
b1 7"
b1 ?"
b1 _"
b1 m
b1 G"
b1 O"
b1 W"
b1 g"
b1 ]
b1 e
b1 u
b1 }
b1 '"
b10 N
b10 V
b10 0"
b10 8"
b10 @"
b10 `"
b10 n
b10 H"
b10 P"
b10 X"
b10 h"
b10 ^
b10 f
b10 v
b10 ~
b10 ("
11
#180
01
#190
b1000 !
b1000 @
b1000 &"
b1010 %"
b10110100 )"
b1010 "
b1010 A
b1010 |
b10111110 !"
b0 #
b0 B
b0 t
b11110 $"
b11 d
b11 #"
b1011 c
b11111000 g
b0 z
b0 \
b0 y
b0 a
b0 [
b0 `
b0 U"
b10 '"
b10 }
b10 u
b10 e
b10 ]
b10 g"
b10 W"
b10 O"
b10 G"
b10 m
b10 _"
b10 ?"
b10 7"
b10 /"
b10 U
b10 M
b1 ("
b1 ~
b1 v
b1 f
b1 ^
b1 h"
b1 X"
b1 P"
b1 H"
b1 n
b1 `"
b1 @"
b1 8"
b1 0"
b1 V
b1 N
11
#200
01
