verilog/systolic_array_4x4/fsm_pe.v
module fsm_pe (RD, FDi, clk, rst, GD, FDo, result, result_ld);
	parameter DATA_WIDTH=16,
			reset=0,
			calc_0=1,
			calc_1=2,
			ld_result=3,
			drain_0=4,
			drain_1=5;
	
	input [(2*DATA_WIDTH)-1:0] RD;
	input [DATA_WIDTH-1:0] FDi;
	input clk, rst, result_ld;
	
	output reg [DATA_WIDTH-1:0] FDo;
	output reg [(2*DATA_WIDTH)-1:0] GD;
	output reg [(2*DATA_WIDTH)-1:0] result;
	
	wire [(2*DATA_WIDTH)-1:0] multi;
	
	reg[2:0]  p_state, n_state;	
	
	
	always @ (p_state,result_ld)
	
    		begin
            
     		   case (p_state)
        
			reset: // state 0
			begin
				result <= 0;
				FDo <= 0;
				GD <= 0;
				
				// next state
				n_state=calc_0;
			end
			
			calc_0: // state 1
			begin
				result <= result + multi;
				FDo <= FDi;
				GD <= RD;
				
				// next state
				if (result_ld)
					n_state=ld_result;
				else
					n_state=calc_1;			
			end
	
			calc_1: // state 2
			begin
				result <= result + multi;
				FDo <= FDi;
				GD <= RD;
				
				// next state
				if (result_ld)
					n_state=ld_result;
				else
					n_state=calc_0;			
			end
	
			ld_result: // state 3
			begin
				GD <= result;
				
				// next state
				n_state=drain_0;
			end
			
			drain_0: // state 4
			begin
				GD <= RD;
				
				// next state
				n_state=drain_1;
			end
			
			drain_1: // state 5
			begin
				GD <= RD;
				
				// next state
				n_state=drain_0;
			end

			default: n_state= reset;

		   endcase
		
	end // end of always
	
	// MAC operation
		assign multi = RD*FDi;
		
	
  	always @ (posedge clk)
  	
    		begin // always    
       			if (rst)
        			   p_state=reset; 
			else
     				   p_state=n_state;
   		 end // always
endmodule

verilog/systolic_array_4x4/systolic_array_4x4.v
`timescale 1ns/1ns
module systolic_array_4x4(
		      FDi0, FDi4, FDi8, FDi12,
		      RD0, RD1, RD2, RD3,
		      clk, rst, result_ld,
		      FDo_0, FDo_4, FDo_8, FDo_12,
		      sa_GD0, sa_GD1, sa_GD2, sa_GD3);
	parameter DATA_WIDTH=16;
	
	input [DATA_WIDTH-1:0] FDi0, FDi4, FDi8, FDi12;
	input [(2*DATA_WIDTH)-1:0] RD0, RD1, RD2, RD3;
	input clk, rst, result_ld;
	
	output [(2*DATA_WIDTH)-1:0] sa_GD0, sa_GD1, sa_GD2, sa_GD3;
	output [DATA_WIDTH-1:0] FDo_0, FDo_4, FDo_8, FDo_12;
	
	
	wire [(2*DATA_WIDTH)-1:0] result[0:15];
	
		
	wire [(2*DATA_WIDTH)-1:0] GD[0:15];
	wire [DATA_WIDTH-1:0] FDo[0:15];
	

	//from north and west
	fsm_pe P0 (RD0, FDi0, clk, rst, GD[0], FDo_0, result[0], result_ld);
	//from north
	fsm_pe P1 (RD1, FDo_0, clk, rst, GD[1], FDo[1], result[1], result_ld);
	fsm_pe P2 (RD2, FDo[1], clk, rst, GD[2], FDo[2], result[2], result_ld);
	fsm_pe P3 (RD3, FDo[2], clk, rst, GD[3], FDo[3], result[3], result_ld);
	
	//from west
	fsm_pe P4 (GD[0], FDi4, clk, rst, GD[4], FDo_4, result[4], result_ld);
	fsm_pe P8 (GD[4], FDi8, clk, rst, GD[8], FDo_8, result[8], result_ld);
	fsm_pe P12 (GD[8], FDi12, clk, rst, sa_GD0, FDo_12, result[12], result_ld);
	
	//no direct inputs
	//second row
	fsm_pe P5 (GD[1], FDo_4, clk, rst, GD[5], FDo[5], result[5], result_ld);
	fsm_pe P6 (GD[2], FDo[5], clk, rst, GD[6], FDo[6], result[6], result_ld);
	fsm_pe P7 (GD[3], FDo[6], clk, rst, GD[7], FDo[7], result[7], result_ld);
	//third row
	fsm_pe P9 (GD[5], FDo_8, clk, rst, GD[9], FDo[9], result[9], result_ld);
	fsm_pe P10 (GD[6], FDo[9], clk, rst, GD[10], FDo[10], result[10], result_ld);
	fsm_pe P11 (GD[7], FDo[10], clk, rst, GD[11], FDo[11], result[11], result_ld);
	//fourth row
	fsm_pe P13 (GD[9], FDo_12, clk, rst, sa_GD1, FDo[13], result[13], result_ld);
	fsm_pe P14 (GD[10], FDo[13], clk, rst, sa_GD2, FDo[14], result[14], result_ld);
	fsm_pe P15 (GD[11], FDo[14], clk, rst, sa_GD3, FDo[15], result[15], result_ld);
	
		      
endmodule

verilog/systolic_array_4x4/in_buffer_4x4_2DW.v
module in_buffer_4x4_2DW (in, read, clk, full, empty, out0, out1, out2, out3);
	
	parameter DATA_WIDTH=16,
			D_2_W=(2*DATA_WIDTH),	
			n=4,
			m=7;
	
	input [D_2_W-1:0] in;
	input clk, read;
	
	output reg[D_2_W-1:0] out0, out1, out2, out3;
	output reg full, empty;
	
	integer i=0, j=0, k=0;

	reg [D_2_W-1:0] mem[0:(m-1)][0:(n-1)];
	
	
	always @ (posedge clk) begin
	
		if ((~read) && (i<m) && (j<n)) begin
			
			mem [i][j]<=in;
			
			//$display ("-----if 1-----");
			//$display ("mem [%d][%d]=%d", i, j, in);  
			j=j+1;
		end
		
		else if ((~read) && (i<(m-1)) && (j>(n-1))) begin
			j=0;
			i=i+1;
			mem [i][j]<=in;
			//$display ("mem [%d][%d]=%d", i, j, in); 
			//$display ("----------");
			j=1;
		end
		
		else if ((~read) && (i>(m-1))) begin
		
			full<=1;
			$display ("Buffer is full");  
				
		end
	
		else if ((read) && (k<(m))) begin
		
			out0 <= mem[k][0];
			out1 <= mem[k][1];
			out2 <= mem[k][2];
			out3 <= mem[k][3];
			
			k=k+1;
		end
		
		else if ((read) && (k>(m-1))) begin
		
			$display ("Buffer is empty"); 
			empty<=1;
			
		end
				
	end // always
		
endmodule

verilog/systolic_array_4x4/in_buffer_4x4_DW.v
module in_buffer_4x4_DW (in, read, clk, full, empty, out0, out1, out2, out3);
	
	parameter DATA_WIDTH=16,
			n=4,
			m=7;
	
	input [DATA_WIDTH-1:0] in;
	input clk, read;
	
	output reg[DATA_WIDTH-1:0] out0, out1, out2, out3;
	output reg full, empty;
	
	integer i=0, j=0, k=0;

	reg [DATA_WIDTH-1:0] mem[0:(m-1)][0:(n-1)];
	
	
	always @ (posedge clk) begin
	
		if ((~read) && (i<m) && (j<n)) begin
			
			mem [i][j]<=in;
			
			//$display ("-----if 1-----");
			//$display ("mem [%d][%d]=%d", i, j, in);  
			j=j+1;
		end
		
		else if ((~read) && (i<(m-1)) && (j>(n-1))) begin
			j=0;
			i=i+1;
			mem [i][j]<=in;
			//$display ("mem [%d][%d]=%d", i, j, in); 
			//$display ("----------");
			j=1;
		end
		
		else if ((~read) && (i>(m-1))) begin
		
			full<=1;
			$display ("Buffer is full");  
				
		end
	
		else if ((read) && (k<(m))) begin
		
			out0 <= mem[k][0];
			out1 <= mem[k][1];
			out2 <= mem[k][2];
			out3 <= mem[k][3];
			
			k=k+1;
		end
		
		else if ((read) && (k>(m-1))) begin
		
			$display ("Buffer is empty"); 
			empty<=1;
			
		end
				
	end // always
		
endmodule

verilog/systolic_array_4x4/three_buffered_systolic_array_4x4.v

module systolic_array_chip_4x4(inA, inB, clk, buf_read, rst, result_ld, GD0, GD1, GD2, GD3);
	
	parameter DATA_WIDTH=16;
	
	input [DATA_WIDTH-1:0] inA;
	input [(2*DATA_WIDTH)-1:0] inB;
	input clk, rst, result_ld,buf_read;
	output [(2*DATA_WIDTH)-1:0] GD0, GD1, GD2, GD3;
	
	wire [DATA_WIDTH-1:0] FDi_sig[0:3];
	wire [(2*DATA_WIDTH)-1:0] RD_sig[0:3];
	//wire [(2*DATA_WIDTH)-1:0] GD_sig[0:3];
	
	wire buf_A_full, buf_A_empty, buf_B_full, buf_B_empty,buf_C_full;
	

	in_buffer_4x4_DW A_bf_inst(
		.in(inA),
		.read(buf_read),
		.clk(clk),
		.full(buf_A_full),
		.empty(buf_A_empty),
		.out0(FDi_sig[0]),
		.out1(FDi_sig[1]),
		.out2(FDi_sig[2]),
		.out3(FDi_sig[3])
	);
	
	in_buffer_4x4_2DW B_bf_inst(
		.in(inB),
		.read(buf_read),
		.clk(clk),
		.full(buf_B_full),
		.empty(buf_B_empty),
		.out0(RD_sig[0]),
		.out1(RD_sig[1]),
		.out2(RD_sig[2]),
		.out3(RD_sig[3])
	);
	
//	outp_buffer outp_buf_inst(
//		.clk(clk),
//		.full(buf_C_full),
//		.in0(GD_sig[0]),
//		.in1(GD_sig[1]),
//		.in2(GD_sig[2]),
//		.in3(GD_sig[3])
//	);
	
	systolic_array_4x4 sys_inst(
		.FDi0(FDi_sig[0]),
		.FDi4(FDi_sig[1]),
		.FDi8(FDi_sig[2]),
		.FDi12(FDi_sig[3]),
		.RD0(RD_sig[0]),
		.RD1(RD_sig[1]),
		.RD2(RD_sig[2]),
		.RD3(RD_sig[3]),
		.clk(clk),
		.rst(rst),
		.result_ld(result_ld),
		.sa_GD0(GD0),
		.sa_GD1(GD1),
		.sa_GD2(GD2),
		.sa_GD3(GD3)
	);

		      
endmodule

verilog/systolic_array_4x4/tb_three_buffered_systolic_array_4x4.v
`timescale 1ns/1ns

module systolic_array_chip_4x4_tb;

parameter DATA_WIDTH=16,
		period=10,
		ld_time=(60*period),
		start_ld=period,
		sys_rst=ld_time+5,
		bf_out_period=(15*period),
		num_of_clk=100;

	reg [DATA_WIDTH-1:0] tb_inA;
	reg [(2*DATA_WIDTH)-1:0] tb_inB;
	wire [(2*DATA_WIDTH)-1:0] tb_GD0, tb_GD1, tb_GD2, tb_GD3;
	
	reg tb_clk, tb_rst, tb_result_ld, tb_buf_read;
	
	integer inFromFile_A,inFromFile_B, A_file,B_file;
	
	systolic_array_chip_4x4 sys_chip_inst(
		.inA(tb_inA),
		.inB(tb_inB),
		.clk(tb_clk),
		.buf_read(tb_buf_read),
		.rst(tb_rst),
		.result_ld(tb_result_ld),
		.GD0(tb_GD0),
		.GD1(tb_GD1),
		.GD2(tb_GD2),
		.GD3(tb_GD3)
	);
	
// Reading B File
initial begin
	
#start_ld; //according to the text bench of buffer B
              
  	B_file=$fopen("B_TB.txt","r");
      
		while (! $feof(B_file)) 
			begin         
			inFromFile_B= $fscanf(B_file,"%d\n",tb_inB);
			#(2*period);                         
		end
                  
	$fclose(B_file);
      
end // End of Reading B

// Reading A File
initial begin
	
#start_ld;
	A_file=$fopen("A_TB.txt","r");
      
	while (! $feof(A_file)) 
		begin         
			inFromFile_A=$fscanf(A_file,"%d\n",tb_inA);
			#(2*period);
	end
                  
	$fclose(A_file);
      
end // End of input file

initial begin // rst 
	tb_rst <= 0;
	tb_clk <= 0;
	#(sys_rst);
	tb_rst <= 1;
	#(period);
	tb_rst <= 0;
end

initial begin // clock
	
	repeat(num_of_clk)
		#period tb_clk <= ~tb_clk;
end

initial begin // buffer read
		
	tb_buf_read=0;
	#ld_time;
	tb_buf_read=1;
end

initial begin // result_ld

	#(ld_time + bf_out_period+75);
	tb_result_ld=1;
	#(2*period);
	tb_result_ld=0;

end
	
initial begin
	$dumpfile("wave_new_v0.3.vcd");
	$dumpvars; //(0, sys_array_tb);
end
			      
endmodule

verilog/systolic_array_4x4/vcd/wave_new_v0.3.vcd
$date
	Tue Jul 25 15:12:32 2023
$end
$version
	Icarus Verilog
$end
$timescale
	1ns
$end
$scope module systolic_array_chip_4x4_tb $end
$var wire 32 ! tb_GD3 [31:0] $end
$var wire 32 " tb_GD2 [31:0] $end
$var wire 32 # tb_GD1 [31:0] $end
$var wire 32 $ tb_GD0 [31:0] $end
$var reg 1 % tb_buf_read $end
$var reg 1 & tb_clk $end
$var reg 16 ' tb_inA [15:0] $end
$var reg 32 ( tb_inB [31:0] $end
$var reg 1 ) tb_result_ld $end
$var reg 1 * tb_rst $end
$var integer 32 + A_file [31:0] $end
$var integer 32 , B_file [31:0] $end
$var integer 32 - inFromFile_A [31:0] $end
$var integer 32 . inFromFile_B [31:0] $end
$scope module sys_chip_inst $end
$var wire 1 % buf_read $end
$var wire 1 & clk $end
$var wire 16 / inA [15:0] $end
$var wire 32 0 inB [31:0] $end
$var wire 1 ) result_ld $end
$var wire 1 * rst $end
$var wire 1 1 buf_B_full $end
$var wire 1 2 buf_B_empty $end
$var wire 1 3 buf_A_full $end
$var wire 1 4 buf_A_empty $end
$var wire 32 5 GD3 [31:0] $end
$var wire 32 6 GD2 [31:0] $end
$var wire 32 7 GD1 [31:0] $end
$var wire 32 8 GD0 [31:0] $end
$scope module A_bf_inst $end
$var wire 1 & clk $end
$var wire 16 9 in [15:0] $end
$var wire 1 % read $end
$var reg 1 4 empty $end
$var reg 1 3 full $end
$var reg 16 : out0 [15:0] $end
$var reg 16 ; out1 [15:0] $end
$var reg 16 < out2 [15:0] $end
$var reg 16 = out3 [15:0] $end
$var integer 32 > i [31:0] $end
$var integer 32 ? j [31:0] $end
$var integer 32 @ k [31:0] $end
$upscope $end
$scope module B_bf_inst $end
$var wire 1 & clk $end
$var wire 32 A in [31:0] $end
$var wire 1 % read $end
$var reg 1 2 empty $end
$var reg 1 1 full $end
$var reg 32 B out0 [31:0] $end
$var reg 32 C out1 [31:0] $end
$var reg 32 D out2 [31:0] $end
$var reg 32 E out3 [31:0] $end
$var integer 32 F i [31:0] $end
$var integer 32 G j [31:0] $end
$var integer 32 H k [31:0] $end
$upscope $end
$scope module sys_inst $end
$var wire 16 I FDi0 [15:0] $end
$var wire 16 J FDi12 [15:0] $end
$var wire 16 K FDi4 [15:0] $end
$var wire 16 L FDi8 [15:0] $end
$var wire 32 M RD0 [31:0] $end
$var wire 32 N RD1 [31:0] $end
$var wire 32 O RD2 [31:0] $end
$var wire 32 P RD3 [31:0] $end
$var wire 1 & clk $end
$var wire 1 ) result_ld $end
$var wire 1 * rst $end
$var wire 32 Q sa_GD3 [31:0] $end
$var wire 32 R sa_GD2 [31:0] $end
$var wire 32 S sa_GD1 [31:0] $end
$var wire 32 T sa_GD0 [31:0] $end
$var wire 16 U FDo_8 [15:0] $end
$var wire 16 V FDo_4 [15:0] $end
$var wire 16 W FDo_12 [15:0] $end
$var wire 16 X FDo_0 [15:0] $end
$scope module P0 $end
$var wire 16 Y FDi [15:0] $end
$var wire 32 Z RD [31:0] $end
$var wire 1 & clk $end
$var wire 1 ) result_ld $end
$var wire 1 * rst $end
$var wire 32 [ multi [31:0] $end
$var reg 16 \ FDo [15:0] $end
$var reg 32 ] GD [31:0] $end
$var reg 3 ^ n_state [2:0] $end
$var reg 3 _ p_state [2:0] $end
$var reg 32 ` result [31:0] $end
$upscope $end
$scope module P1 $end
$var wire 16 a FDi [15:0] $end
$var wire 32 b RD [31:0] $end
$var wire 1 & clk $end
$var wire 1 ) result_ld $end
$var wire 1 * rst $end
$var wire 32 c multi [31:0] $end
$var reg 16 d FDo [15:0] $end
$var reg 32 e GD [31:0] $end
$var reg 3 f n_state [2:0] $end
$var reg 3 g p_state [2:0] $end
$var reg 32 h result [31:0] $end
$upscope $end
$scope module P10 $end
$var wire 1 & clk $end
$var wire 1 ) result_ld $end
$var wire 1 * rst $end
$var wire 32 i multi [31:0] $end
$var wire 32 j RD [31:0] $end
$var wire 16 k FDi [15:0] $end
$var reg 16 l FDo [15:0] $end
$var reg 32 m GD [31:0] $end
$var reg 3 n n_state [2:0] $end
$var reg 3 o p_state [2:0] $end
$var reg 32 p result [31:0] $end
$upscope $end
$scope module P11 $end
$var wire 16 q FDi [15:0] $end
$var wire 1 & clk $end
$var wire 1 ) result_ld $end
$var wire 1 * rst $end
$var wire 32 r multi [31:0] $end
$var wire 32 s RD [31:0] $end
$var reg 16 t FDo [15:0] $end
$var reg 32 u GD [31:0] $end
$var reg 3 v n_state [2:0] $end
$var reg 3 w p_state [2:0] $end
$var reg 32 x result [31:0] $end
$upscope $end
$scope module P12 $end
$var wire 16 y FDi [15:0] $end
$var wire 1 & clk $end
$var wire 1 ) result_ld $end
$var wire 1 * rst $end
$var wire 32 z multi [31:0] $end
$var wire 32 { RD [31:0] $end
$var reg 16 | FDo [15:0] $end
$var reg 32 } GD [31:0] $end
$var reg 3 ~ n_state [2:0] $end
$var reg 3 !" p_state [2:0] $end
$var reg 32 "" result [31:0] $end
$upscope $end
$scope module P13 $end
$var wire 16 #" FDi [15:0] $end
$var wire 1 & clk $end
$var wire 1 ) result_ld $end
$var wire 1 * rst $end
$var wire 32 $" multi [31:0] $end
$var wire 32 %" RD [31:0] $end
$var reg 16 &" FDo [15:0] $end
$var reg 32 '" GD [31:0] $end
$var reg 3 (" n_state [2:0] $end
$var reg 3 )" p_state [2:0] $end
$var reg 32 *" result [31:0] $end
$upscope $end
$scope module P14 $end
$var wire 16 +" FDi [15:0] $end
$var wire 32 ," RD [31:0] $end
$var wire 1 & clk $end
$var wire 1 ) result_ld $end
$var wire 1 * rst $end
$var wire 32 -" multi [31:0] $end
$var reg 16 ." FDo [15:0] $end
$var reg 32 /" GD [31:0] $end
$var reg 3 0" n_state [2:0] $end
$var reg 3 1" p_state [2:0] $end
$var reg 32 2" result [31:0] $end
$upscope $end
$scope module P15 $end
$var wire 16 3" FDi [15:0] $end
$var wire 32 4" RD [31:0] $end
$var wire 1 & clk $end
$var wire 1 ) result_ld $end
$var wire 1 * rst $end
$var wire 32 5" multi [31:0] $end
$var reg 16 6" FDo [15:0] $end
$var reg 32 7" GD [31:0] $end
$var reg 3 8" n_state [2:0] $end
$var reg 3 9" p_state [2:0] $end
$var reg 32 :" result [31:0] $end
$upscope $end
$scope module P2 $end
$var wire 16 ;" FDi [15:0] $end
$var wire 32 <" RD [31:0] $end
$var wire 1 & clk $end
$var wire 1 ) result_ld $end
$var wire 1 * rst $end
$var wire 32 =" multi [31:0] $end
$var reg 16 >" FDo [15:0] $end
$var reg 32 ?" GD [31:0] $end
$var reg 3 @" n_state [2:0] $end
$var reg 3 A" p_state [2:0] $end
$var reg 32 B" result [31:0] $end
$upscope $end
$scope module P3 $end
$var wire 16 C" FDi [15:0] $end
$var wire 32 D" RD [31:0] $end
$var wire 1 & clk $end
$var wire 1 ) result_ld $end
$var wire 1 * rst $end
$var wire 32 E" multi [31:0] $end
$var reg 16 F" FDo [15:0] $end
$var reg 32 G" GD [31:0] $end
$var reg 3 H" n_state [2:0] $end
$var reg 3 I" p_state [2:0] $end
$var reg 32 J" result [31:0] $end
$upscope $end
$scope module P4 $end
$var wire 16 K" FDi [15:0] $end
$var wire 32 L" RD [31:0] $end
$var wire 1 & clk $end
$var wire 1 ) result_ld $end
$var wire 1 * rst $end
$var wire 32 M" multi [31:0] $end
$var reg 16 N" FDo [15:0] $end
$var reg 32 O" GD [31:0] $end
$var reg 3 P" n_state [2:0] $end
$var reg 3 Q" p_state [2:0] $end
$var reg 32 R" result [31:0] $end
$upscope $end
$scope module P5 $end
$var wire 16 S" FDi [15:0] $end
$var wire 32 T" RD [31:0] $end
$var wire 1 & clk $end
$var wire 1 ) result_ld $end
$var wire 1 * rst $end
$var wire 32 U" multi [31:0] $end
$var reg 16 V" FDo [15:0] $end
$var reg 32 W" GD [31:0] $end
$var reg 3 X" n_state [2:0] $end
$var reg 3 Y" p_state [2:0] $end
$var reg 32 Z" result [31:0] $end
$upscope $end
$scope module P6 $end
$var wire 16 [" FDi [15:0] $end
$var wire 32 \" RD [31:0] $end
$var wire 1 & clk $end
$var wire 1 ) result_ld $end
$var wire 1 * rst $end
$var wire 32 ]" multi [31:0] $end
$var reg 16 ^" FDo [15:0] $end
$var reg 32 _" GD [31:0] $end
$var reg 3 `" n_state [2:0] $end
$var reg 3 a" p_state [2:0] $end
$var reg 32 b" result [31:0] $end
$upscope $end
$scope module P7 $end
$var wire 16 c" FDi [15:0] $end
$var wire 32 d" RD [31:0] $end
$var wire 1 & clk $end
$var wire 1 ) result_ld $end
$var wire 1 * rst $end
$var wire 32 e" multi [31:0] $end
$var reg 16 f" FDo [15:0] $end
$var reg 32 g" GD [31:0] $end
$var reg 3 h" n_state [2:0] $end
$var reg 3 i" p_state [2:0] $end
$var reg 32 j" result [31:0] $end
$upscope $end
$scope module P8 $end
$var wire 16 k" FDi [15:0] $end
$var wire 32 l" RD [31:0] $end
$var wire 1 & clk $end
$var wire 1 ) result_ld $end
$var wire 1 * rst $end
$var wire 32 m" multi [31:0] $end
$var reg 16 n" FDo [15:0] $end
$var reg 32 o" GD [31:0] $end
$var reg 3 p" n_state [2:0] $end
$var reg 3 q" p_state [2:0] $end
$var reg 32 r" result [31:0] $end
$upscope $end
$scope module P9 $end
$var wire 16 s" FDi [15:0] $end
$var wire 32 t" RD [31:0] $end
$var wire 1 & clk $end
$var wire 1 ) result_ld $end
$var wire 1 * rst $end
$var wire 32 u" multi [31:0] $end
$var reg 16 v" FDo [15:0] $end
$var reg 32 w" GD [31:0] $end
$var reg 3 x" n_state [2:0] $end
$var reg 3 y" p_state [2:0] $end
$var reg 32 z" result [31:0] $end
$upscope $end
$upscope $end
$upscope $end
$upscope $end
$enddefinitions $end
#0
$dumpvars
bx z"
bx y"
bx x"
bx w"
bx v"
bx u"
bx t"
bx s"
bx r"
bx q"
bx p"
bx o"
bx n"
bx m"
bx l"
bx k"
bx j"
bx i"
bx h"
bx g"
bx f"
bx e"
bx d"
bx c"
bx b"
bx a"
bx `"
bx _"
bx ^"
bx ]"
bx \"
bx ["
bx Z"
bx Y"
bx X"
bx W"
bx V"
bx U"
bx T"
bx S"
bx R"
bx Q"
bx P"
bx O"
bx N"
bx M"
bx L"
bx K"
bx J"
bx I"
bx H"
bx G"
bx F"
bx E"
bx D"
bx C"
bx B"
bx A"
bx @"
bx ?"
bx >"
bx ="
bx <"
bx ;"
bx :"
bx 9"
bx 8"
bx 7"
bx 6"
bx 5"
bx 4"
bx 3"
bx 2"
bx 1"
bx 0"
bx /"
bx ."
bx -"
bx ,"
bx +"
bx *"
bx )"
bx ("
bx '"
bx &"
bx %"
bx $"
bx #"
bx ""
bx !"
bx ~
bx }
bx |
bx {
bx z
bx y
bx x
bx w
bx v
bx u
bx t
bx s
bx r
bx q
bx p
bx o
bx n
bx m
bx l
bx k
bx j
bx i
bx h
bx g
bx f
bx e
bx d
bx c
bx b
bx a
bx `
bx _
bx ^
bx ]
bx \
bx [
bx Z
bx Y
bx X
bx W
bx V
bx U
bx T
bx S
bx R
bx Q
bx P
bx O
bx N
bx M
bx L
bx K
bx J
bx I
b0 H
b0 G
b0 F
bx E
bx D
bx C
bx B
bx A
b0 @
b0 ?
b0 >
bx =
bx <
bx ;
bx :
bx 9
bx 8
bx 7
bx 6
bx 5
x4
x3
x2
x1
bx 0
bx /
bx .
bx -
bx ,
bx +
0*
x)
bx (
bx '
0&
0%
bx $
bx #
bx "
bx !
$end
#10
b1 ?
b1 G
1&
b1 -
b1001 '
b1001 /
b1001 9
b10000000000000000000000000000100 +
b1 .
b11 (
b11 0
b11 A
b10000000000000000000000000000011 ,
#20
0&
#30
b10 G
b10 ?
1&
b0 '
b0 /
b0 9
b0 (
b0 0
b0 A
#40
0&
#50
b11 ?
b11 G
1&
#60
0&
#70
b100 G
b100 ?
1&
#80
0&
#90
b1 >
b1 ?
b1 F
b1 G
1&
b111 '
b111 /
b111 9
b1 (
b1 0
b1 A
#100
0&
#110
b10 G
b10 ?
1&
b110 '
b110 /
b110 9
b1000 (
b1000 0
b1000 A
#120
0&
#130
b11 ?
b11 G
1&
b0 '
b0 /
b0 9
b0 (
b0 0
b0 A
#140
0&
#150
b100 G
b100 ?
1&
#160
0&
#170
b10 >
b1 ?
b10 F
b1 G
1&
b1100 '
b1100 /
b1100 9
b101 (
b101 0
b101 A
#180
0&
#190
b10 G
b10 ?
1&
b111 '
b111 /
b111 9
b1101 (
b1101 0
b1101 A
#200
0&
#210
b11 ?
b11 G
1&
b100 '
b100 /
b100 9
b110 (
b110 0
b110 A
#220
0&
#230
b100 G
b100 ?
1&
b0 '
b0 /
b0 9
b0 (
b0 0
b0 A
#240
0&
#250
b11 >
b1 ?
b11 F
b1 G
1&
b1010 '
b1010 /
b1010 9
b1 (
b1 0
b1 A
#260
0&
#270
b10 G
b10 ?
1&
b1101 '
b1101 /
b1101 9
b1010 (
b1010 0
b1010 A
#280
0&
#290
b11 ?
b11 G
1&
b11 '
b11 /
b11 9
b101 (
b101 0
b101 A
#300
0&
#310
b100 G
b100 ?
1&
b1 '
b1 /
b1 9
b100 (
b100 0
b100 A
#320
0&
#330
b100 >
b1 ?
b100 F
b1 G
1&
b0 '
b0 /
b0 9
b0 (
b0 0
b0 A
#340
0&
#350
b10 G
b10 ?
1&
b1010 '
b1010 /
b1010 9
b10 (
b10 0
b10 A
#360
0&
#370
b11 ?
b11 G
1&
b10 '
b10 /
b10 9
b1 (
b1 0
b1 A
#380
0&
#390
b100 G
b100 ?
1&
b11 '
b11 /
b11 9
b10 (
b10 0
b10 A
#400
0&
#410
b101 >
b1 ?
b101 F
b1 G
1&
b0 '
b0 /
b0 9
b0 (
b0 0
b0 A
#420
0&
#430
b10 G
b10 ?
1&
#440
0&
#450
b11 ?
b11 G
1&
b101 '
b101 /
b101 9
b101 (
b101 0
b101 A
#460
0&
#470
b100 G
b100 ?
1&
b1100 '
b1100 /
b1100 9
b11 (
b11 0
b11 A
#480
0&
#490
b110 >
b1 ?
b110 F
b1 G
1&
b0 '
b0 /
b0 9
b0 (
b0 0
b0 A
#500
0&
#510
b10 G
b10 ?
1&
#520
0&
#530
b11 ?
b11 G
1&
#540
0&
#550
b100 G
b100 ?
1&
b1101 '
b1101 /
b1101 9
b1000 (
b1000 0
b1000 A
#560
0&
#570
1&
#580
0&
#590
1&
#600
0&
1%
#605
1*
#610
b0 M"
b0 ]
b0 L"
b0 c
b0 X
b0 \
b0 a
b0 `
b0 U"
b0 e
b0 T"
b0 ="
b0 d
b0 ;"
b0 h
b0 ]"
b0 ?"
b0 \"
b0 E"
b0 >"
b0 C"
b0 B"
b0 e"
b0 G"
b0 d"
b0 F"
b0 J"
b0 m"
b0 O"
b0 l"
b0 V
b0 N"
b0 S"
b0 R"
b0 z
b0 {
b0 o"
b0 u"
b0 U
b0 n"
b0 s"
b0 r"
b0 $
b0 8
b0 T
b0 }
b0 $"
b0 W
b0 |
b0 #"
b0 ""
b0 W"
b0 t"
b0 V"
b0 ["
b0 Z"
b0 i
b0 j
b0 _"
b0 ^"
b0 c"
b0 b"
b0 r
b0 s
b0 g"
b0 f"
b0 j"
b0 %"
b0 w"
b0 k
b0 v"
b0 z"
b0 -"
b0 m
b0 ,"
b0 l
b0 q
b0 p
b0 5"
b0 u
b0 4"
b0 t
b0 x
b0 #
b0 7
b0 S
b0 '"
b0 &"
b0 +"
b0 *"
b0 "
b0 6
b0 R
b0 /"
b0 ."
b0 3"
b0 2"
b0 !
b0 5
b0 Q
b0 7"
b0 6"
b0 :"
b0 =
b0 J
b0 y
b0 <
b0 L
b0 k"
b0 ;
b0 K
b0 K"
b11011 [
b1001 :
b1001 I
b1001 Y
b0 E
b0 P
b0 D"
b0 D
b0 O
b0 <"
b0 C
b0 N
b0 b
b11 B
b11 M
b11 Z
b1 ^
b1 f
b1 @"
b1 H"
b1 P"
b1 p"
b1 ~
b1 X"
b1 `"
b1 h"
b1 x"
b1 n
b1 v
b1 ("
b1 0"
b1 8"
b1 @
b1 H
b0 _
b0 g
b0 A"
b0 I"
b0 Q"
b0 q"
b0 !"
b0 Y"
b0 a"
b0 i"
b0 y"
b0 o
b0 w
b0 )"
b0 1"
b0 9"
1&
#615
0*
#620
0&
#630
b10010 M"
b11 ]
b11 L"
b1001000 c
b1001 X
b1001 \
b1001 a
b11011 `
b1000 C
b1000 N
b1000 b
b1 B
b1 M
b1 Z
b110 ;
b110 K
b110 K"
b111 [
b111 :
b111 I
b111 Y
b10 8"
b10 0"
b10 ("
b10 v
b10 n
b10 x"
b10 h"
b10 `"
b10 X"
b10 ~
b10 p"
b10 P"
b10 H"
b10 @"
b10 f
b10 ^
b1 9"
b1 1"
b1 )"
b1 w
b1 o
b1 y"
b1 i"
b1 a"
b1 Y"
b1 !"
b1 q"
b1 Q"
b1 I"
b1 A"
b1 g
b1 _
b10 H
b10 @
1&
#640
0&
#650
b1 ]
b1 L"
b111 X
b111 \
b111 a
b100010 `
b110000 U"
b1000 e
b1000 T"
b110110 ="
b1001 d
b1001 ;"
b1001000 h
b1100 m"
b11 O"
b11 l"
b110 V
b110 N"
b110 S"
b10010 R"
b100 <
b100 L
b100 k"
b111 M"
b111 ;
b111 K
b111 K"
b1100 :
b1100 I
b1100 Y
b110 D
b110 O
b110 <"
b1011011 c
b1101 C
b1101 N
b1101 b
b111100 [
b101 B
b101 M
b101 Z
b1 ^
b1 f
b1 @"
b1 H"
b1 P"
b1 p"
b1 ~
b1 X"
b1 `"
b1 h"
b1 x"
b1 n
b1 v
b1 ("
b1 0"
b1 8"
b11 @
b11 H
b10 _
b10 g
b10 A"
b10 I"
b10 Q"
b10 q"
b10 !"
b10 Y"
b10 a"
b10 i"
b10 y"
b10 o
b10 w
b10 )"
b10 1"
b10 9"
1&
#660
0&
